{
	"ua": "",
	"homeUrl": "https://ddrk.me",
    "cateNode": "//ul[@class=' dropdown-menu']/li[contains(@id,'menu-item-')]/a[contains(@href,'category') and not(contains(@href,'vip'))]",
	"cateName": "/text()",
	"cateId": "/@href",
    "cateIdR": "",
	"cateManual": {},


    "homeVodNode": "//div[@class='post-box-list']//div[@class='post-box-container']",
	"homeVodName": "substring-before(//div[@class='post-box-text']/h2[@class='post-box-title']/a/text(), \"(\")",
	"homeVodId": "//h2[@class='post-box-title']/a/@href",
    "homeVodIdR": "substring-after((\\w+), \"https://ddrk.me/\")",
	"homeVodImg": "substring-before(substring-after(//div[@class='post-box-image']/@style, \"background-image: url(\"), \")\")",
	"homeVodMark": "substring-before(substring-after(//div[@class='post-box-text']/h2[@class='post-box-title']/a/text(), \"(\"), \")\")",

	"cateUrl": "{cateId}/page/{catePg}/",
	"cateVodNode": "//div[@class='post-box-list']//div[@class='post-box-container']",
	"cateVodName": "substring-before(//div[@class='post-box-text']/h2[@class='post-box-title']/a/text(), \"(\")",
	"cateVodId": "substring-after(//h2[@class='post-box-title']/a/@href, \"https://ddrk.me/\")",
	"cateVodImg": "substring-before(substring-after(//div[@class='post-box-image']/@style, \"background-image: url(\"), \");\")",
	"cateVodMark": "substring-before(substring-after(//div[@class='post-box-text']/h2[@class='post-box-title']/a/text(), \"(\"), \")\")",

	"dtUrl": "https://ddrk.me/{vid}/",
	"dtNode": "//div[@class='post-content']",
	"dtName": "//div[@class='title']/a[@class='cute']/text()",
	"dtNameR": "",
	"dtImg": "//div[@class='post']/img/@src",
	"dtImgR": "",
    // // 视频分类
	// "dtCate": "//div[@class='col-md-8']//span[@class='info-label' and contains(text(), '类型')]/parent::*/following-sibling::*/text()",
	// "dtCateR": "",
    // // 视频年份
	// "dtYear": "//div[@class='col-md-8']//span[@class='info-label' and contains(text(), '日期')]/parent::*/following-sibling::*/text()",
	// "dtYearR": "",
    // // 视频地区
	// "dtArea": "//div[@class='col-md-8']//span[@class='info-label' and contains(text(), '国家')]/parent::*/following-sibling::*/text()",
	// "dtAreaR": "",
    // // 视频状态
	// "dtMark": "//div[@class='col-md-8']//span[@class='info-label' and contains(text(), '状态')]/parent::*/following-sibling::*/text()",
	// "dtMarkR": "",
    // // 主演
	// "dtActor": "//div[@class='col-md-8']//span[@class='info-label' and contains(text(), '主演')]/parent::*/following-sibling::*/text()",
	// "dtActorR": "",
    // // 导演
	// "dtDirector": "//div[@class='col-md-8']//span[@class='info-label' and contains(text(), '导演')]/parent::*/following-sibling::*/text()",
	// "dtDirectorR": "",
    // // 视频简介
	// "dtDesc": "//p[@class='summary']/text()",
	// "dtDescR": "",
	"dtFromNode": "//div[@class='entry']/p[1]",
	"dtFromName": "//text()",
	"dtFromNameR": "",
	"dtUrlNode": "//div[@class='wp-playlist-tracks']",
	"dtUrlSubNode": "//div[contains(@class,'wp-playlist-item')]/a",
	"dtUrlId": "substring-before(/text(), \".\")",
	"dtUrlIdR": "",
	"dtUrlName": "/text()",
	"dtUrlNameR": "",
	"playUrl": "https://ddrk.me/{playUrl}",
	"playUa": "",
	"searchUrl": "",
    
	"scVodNode": "//div[@class='movie-item']/a",
	"scVodName": "/@title",
	"scVodId": "/@href",
	"scVodIdR": "/show/(\\w+).html",
	"scVodImg": "/img/@src",
	"scVodMark": "/button/text()"
}