{
    "author":"baddychen",
	"ua": "",
    "homeUrl": "https://www.douyu.com/",
    "cateManual": {"英雄联盟":"g_LOL","一起看":"g_yqk"},
	"homeVodNode": "//ul[@class='layout-Cover-list']/li/div/a",
	"homeVodName": "//h3[@class='DyListCover-intro']/text()",
	"homeVodId": "/@href",
	"homeVodIdR": "(\\w+)",
	"homeVodImg": "//picture[contains(@class,'DyImg-content is-normal')]/img/@src",
	"homeVodImgR": "\\S+(http\\S+)",
	"homeVodMark": "concat(/a[contains(@class,'video-info')]/em/text(),'-',/a[contains(@class,'video-info')]/p/em/text(),'-',/span/span[2]/i[2]/text())",
	"cateUrl": "https://www.douyu.com/gapi/rkc/directory/mixList/2_208/{catePg}",
	"cateVodNode": "json:rl",
	"cateVodName": "rn",
	"cateVodId": "rid",
	"cateVodIdR": "(\\w+)",
	"cateVodImg": "rs1",
	"cateVodImgR": "",
	"cateVodMark": "concat(/a[contains(@class,'video-info')]/em/text(),'-',/a[contains(@class,'video-info')]/p/em/text(),'-',/span/span[2]/i[2]/text())",
	"dtUrl": "https://www.huya.com/{vid}",
	"dtNode": "//body",
	"dtName": "//div[@class='host-info']/h1/text()",
	"dtNameR": "",
	"dtImg": "//div[@class='host-pic']/img/@src",
	"dtImgR": "\\S+(http\\S+)",
    "dtCate": "//span[@class='host-channel']/a[2]/text()",
    "dtArea": "//span[@class='host-channel']/a[1]/text()",
	"dtFromNode": "//h3[@class='host-name']",
	"dtFromName": "/text()",
	"dtFromNameR": "",
	"dtUrlNode": "//ul[@class='sidebar-icon-list']",
	"dtUrlSubNode": "/li[contains(@class,'allLive')]/a",
	"dtUrlId": "@eid_desc",
	"dtUrlIdR": "\\S+/(\\S+)",
	"dtUrlName": "/span/text()",
	"dtUrlNameR": "",
    "playUrl": "https://hd.huya.com/h5/liveshare/index.html?lp={playUrl}",
	//"playUrl": "https://hd.huya.com/h5/liveshare/index.html?type=middlepage&rso=wap-live-share&gameid=2&lp={playUrl}&",
    "playUa": "Mozilla/5.0 (Windows NT 10.0; Win64; x64) AppleWebKit/537.36 (KHTML, like Gecko) Chrome/98.0.4758.102 Safari/537.36",
	"searchUrl": "https://www.huya.com/search?hsk={wd}",
	"scVodNode": "//ul[@class='js-live-list']/li",
	"scVodName": "/a[@class='title new-clickstat']/@title",
	"scVodId": "/a[@class='title new-clickstat']/@href",
	"scVodIdR": "https://www.huya.com/(\\w+)",
	"scVodImg": "/a[@class='video-info new-clickstat']/img/@src",
	"scVodMark": ""
}